loaders/__init__.py
loaders/colours/__init__.py
pyloaders-0.0.4.dist-info/LICENSE
pyloaders-0.0.4.dist-info/METADATA
pyloaders-0.0.4.dist-info/WHEEL
pyloaders-0.0.4.dist-info/top_level.txt
pyloaders-0.0.4.dist-info/RECORD
