Metadata-Version: 2.1
Name: pyloaders
Version: 0.0.4
Summary: Basic animated ASCII loaders for Python scripts
Home-page: https://gitlab.com/ml394/pyloaders.git
Author: Matthew Levy
Author-email: matt@webkolektiv.com
License: GPL
Platform: UNKNOWN
Classifier: Programming Language :: Python :: 3
Classifier: Operating System :: OS Independent
